paste_it/__init__.py
paste_it/command_line.py
paste_it-0.1.2.dist-info/entry_points.txt
paste_it-0.1.2.dist-info/LICENSE
paste_it-0.1.2.dist-info/WHEEL
paste_it-0.1.2.dist-info/METADATA
paste_it-0.1.2.dist-info/RECORD
