Metadata-Version: 2.1
Name: paste_it
Version: 0.1.2
Summary: a cli script and tiny library to upload files to pastebin
Home-page: https://github.com/advaithm/paste_it
Author: nullrequest
Author-email: advaith.madhukar@gmail.com
Requires-Python: >=3.8
Classifier: Development Status :: 2 - Pre-Alpha
Classifier: Environment :: Console
Classifier: Intended Audience :: Customer Service
Classifier: License :: OSI Approved :: GNU General Public License v3 (GPLv3)
Classifier: Natural Language :: English
Classifier: Operating System :: OS Independent
Classifier: Programming Language :: Python :: 3 :: Only
Classifier: Programming Language :: Python :: 3.8
Classifier: Programming Language :: Python :: 3.9
Requires-Dist: requests>=2.25.1
Requires-Dist: rich>=9.13.0 ;python_version in '3.8,3.8'
